py2bin/__init__.py
py2bin-0.1.1.dist-info/LICENSE
py2bin-0.1.1.dist-info/METADATA
py2bin-0.1.1.dist-info/WHEEL
py2bin-0.1.1.dist-info/entry_points.txt
py2bin-0.1.1.dist-info/top_level.txt
py2bin-0.1.1.dist-info/RECORD
